idppnpdongle/__init__.py
idppnpdongle/pnpdongle.py
idppnpdongle-1.0.4.dist-info/LICENSE
idppnpdongle-1.0.4.dist-info/WHEEL
idppnpdongle-1.0.4.dist-info/METADATA
idppnpdongle-1.0.4.dist-info/RECORD
