Metadata-Version: 2.1
Name: idppnpdongle
Version: 1.0.4
Summary: Module for interfacing with Inmarsat's IDP Plug-N-Play device.
Home-page: https://github.com/inmarsat-enterprise/idp-pnpdongle
License: Apache-2.0
Keywords: satellite,iot,idp,isatdata pro
Author: G.Bruce-Payne
Author-email: geoff.bruce-payne@inmarsat.com
Requires-Python: >=3.7,<4.0
Classifier: License :: OSI Approved :: Apache Software License
Classifier: Programming Language :: Python :: 3
Classifier: Programming Language :: Python :: 3.7
Classifier: Programming Language :: Python :: 3.8
Classifier: Programming Language :: Python :: 3.9
Requires-Dist: gpiozero (>=1.5.1,<2.0.0)
Requires-Dist: idpmodem (>=1.1.9,<2.0.0)
Requires-Dist: pigpio (>=1.78,<2.0)
Project-URL: Repository, https://github.com/inmarsat-enterprise/idp-pnpdongle
